osstorchconnector-1.1.0.dist-info/LICENSE
osstorchconnector-1.1.0.dist-info/WHEEL
osstorchconnector-1.1.0.dist-info/RECORD
osstorchconnector-1.1.0.dist-info/top_level.txt
osstorchconnector-1.1.0.dist-info/METADATA
osstorchconnector/_oss_bucket_iterable.py
osstorchconnector/oss_checkpoint.py
osstorchconnector/__init__.py
osstorchconnector/oss_map_dataset.py
osstorchconnector/_oss_tar_iterable.py
osstorchconnector/oss_iterable_dataset.py
osstorchconnector/_oss_client.py
osstorchconnector/_oss_connector/oss_connector.pyi
osstorchconnector/_oss_connector/oss_connector.cpython-38-x86_64-linux-gnu.so
osstorchconnector/_oss_connector/__init__.py
